google_sheets_helper/__init__.py
google_sheets_helper/client.py
google_sheets_helper/exceptions.py
google_sheets_helper/py.typed
google_sheets_helper/utils.py
google_sheets_helper-2.0.7.dist-info/LICENSE
google_sheets_helper-2.0.7.dist-info/METADATA
google_sheets_helper-2.0.7.dist-info/WHEEL
google_sheets_helper-2.0.7.dist-info/RECORD
