Metadata-Version: 2.3
Name: google-sheets-helper
Version: 2.0.7
Summary: Lightweight helper module to extract data from Google Sheets and Excel files as list of dictionaries
License: MIT
Keywords: google-sheets,excel,etl,data-extraction,lightweight
Author: Joao Brito
Requires-Python: >=3.11,<3.15
Classifier: Development Status :: 5 - Production/Stable
Classifier: Intended Audience :: Developers
Classifier: Intended Audience :: Information Technology
Classifier: License :: OSI Approved :: MIT License
Classifier: Operating System :: OS Independent
Classifier: Programming Language :: Python :: 3
Classifier: Programming Language :: Python :: 3.11
Classifier: Programming Language :: Python :: 3.12
Classifier: Programming Language :: Python :: 3.13
Classifier: Programming Language :: Python :: 3.14
Classifier: Topic :: Software Development :: Libraries :: Python Modules
Classifier: Topic :: Internet :: WWW/HTTP :: Dynamic Content
Classifier: Typing :: Typed
Requires-Dist: google-api-python-client (>=2.0.0)
Requires-Dist: google-auth (>=2.0.0)
Requires-Dist: google-auth-httplib2 (>=0.1.0)
Requires-Dist: google-auth-oauthlib (>=0.5.0)
Requires-Dist: gspread (>=6.0.0)
Requires-Dist: python-calamine (>=0.4.0,<0.5.0)
Project-URL: Documentation, https://github.com/machado000/google-sheets-helper#readme
Project-URL: Homepage, https://github.com/machado000/google-sheets-helper
Project-URL: Issues, https://github.com/machado000/google-sheets-helper/issues
